odinn/queue.py
odinn-0.1.2.dist-info/METADATA
odinn-0.1.2.dist-info/WHEEL
odinn-0.1.2.dist-info/top_level.txt
odinn-0.1.2.dist-info/RECORD
