Metadata-Version: 2.4
Name: odinn
Version: 0.1.2
Summary: Add your description here
Author-email: Teraflop AI <enrico@teraflop.ai>
Classifier: Typing :: Typed
Classifier: Intended Audience :: Developers
Classifier: Programming Language :: Python :: 3.10
Classifier: Programming Language :: Python :: 3.11
Classifier: Programming Language :: Python :: 3.12
Classifier: Programming Language :: Python :: 3.13
Classifier: Topic :: Software Development :: Libraries :: Python Modules
Requires-Python: >=3.12
Requires-Dist: courlan>=1.3.2
Requires-Dist: lmdb>=1.7.3
Requires-Dist: pyfusefilter>=1.2.1
Requires-Dist: rocksdict>=0.3.27
